Metadata-Version: 2.1
Name: english-dict
Version: 1.1.1
Summary: Simple, storage efficient solution to find definitions with ease.
Author: dsochamp
Keywords: dictionary,meaning,english,easy to use,English Dictionary,english dictionary
Classifier: Development Status :: 3 - Alpha
Classifier: Intended Audience :: Developers
Classifier: Intended Audience :: Education
Classifier: Natural Language :: English
Requires-Dist: bs4
